{
  "type": "minecraft:chest",
  "pools": [
    {
      "rolls": 3,
      "entries": [
        {
          "type": "minecraft:loot_table",
          "value": "shanger:chest/trash",
          "weight": 1
        }
      ]
    },
    {
      "rolls": 1,
      "entries": [
        {
          "type": "minecraft:loot_table",
          "value": "shanger:chest/pot2",
          "weight": 1
        },
        {
          "type": "minecraft:loot_table",
          "value": "shanger:chest/pot1",
          "weight": 9
        },
        {
          "type": "minecraft:loot_table",
          "value": "shanger:chest/util",
          "weight": 60
        }
      ]
    },
    {
      "rolls": {
        "type": "minecraft:uniform",
        "min": 1,
        "max": 2
      },
      "entries": [
        {
          "type": "minecraft:loot_table",
          "value": "shanger:chest/food"
        },
        {
          "type": "minecraft:loot_table",
          "value": "shanger:chest/block"
        }
      ],
      "functions": []
    },
    {
      "rolls": {
        "min": 1,
        "max": 2
      },
      "entries": [
        {
          "type": "minecraft:loot_table",
          "value": "shanger:chest/gear/t1/armor4",
          "weight": 1
        },
        {
          "type": "minecraft:loot_table",
          "value": "shanger:chest/gear/t1/armor3",
          "weight": 5
        },
        {
          "type": "minecraft:loot_table",
          "value": "shanger:chest/gear/t1/armor2",
          "weight": 20
        },
        {
          "type": "minecraft:loot_table",
          "value": "shanger:chest/gear/t1/armor1",
          "weight": 40
        }
      ]
    },
    {
      "rolls": {
        "min": 0,
        "max": 1
      },
      "entries": [
        {
          "type": "minecraft:loot_table",
          "value": "shanger:chest/gear/t1/tools",
          "weight": 1
        }
      ]
    }
  ],
  "functions": []
}