{
    "providers": [
        {
            "type": "reference",
            "id": "minecraft:include/space"
        },
        {
            "type": "reference",
            "id": "minecraft:include/unifont"
        },
        { "type": "space",
            "advances": {
                "\uF000": -36,
                "\uF001": -151,
                "\uEfaf": -1,
                "\uEff1": -8,
                "\uEff2": 5,
                "\uEff3": -9,
                "\uEff4": 4,
                "\uEff5": -8.5,
                "\uEff6": 4.5,
                "\uEff7": -6.5,
                "\uEff8": 6.5
            }
        },

        { "type": "bitmap", "file": "starlight:font/custom_book_look_1.png",
        "height": 182, "ascent": 37, "chars": ["\uE001"] },
        { "type": "bitmap", "file": "starlight:font/custom_book_look_2.png",
        "height": 182, "ascent": 46, "chars": ["\uE002"] },

        { "type": "bitmap", "file": "starlight:font/custom_books/greenhouse_book_left.png",
        "height": 182, "ascent": 37, "chars": ["\uE011"] },
        { "type": "bitmap", "file": "starlight:font/custom_books/greenhouse_book_right.png",
        "height": 182, "ascent": 46, "chars": ["\uE012"] },
        { "type": "bitmap", "file": "starlight:font/custom_books/greenhouse_book_arrow_left.png",
        "height": 182, "ascent": 37, "chars": ["\uE013"] },
        { "type": "bitmap", "file": "starlight:font/custom_books/greenhouse_book_arrow_right.png",
        "height": 182, "ascent": 46, "chars": ["\uE014"] },

        { "type": "bitmap", "file": "starlight:font/custom_books/server_room_book_left.png",
        "height": 182, "ascent": 37, "chars": ["\uE021"] },
        { "type": "bitmap", "file": "starlight:font/custom_books/server_room_book_right.png",
        "height": 182, "ascent": 46, "chars": ["\uE022"] },
        { "type": "bitmap", "file": "starlight:font/custom_books/server_room_book_arrow_left.png",
        "height": 182, "ascent": 37, "chars": ["\uE023"] },
        { "type": "bitmap", "file": "starlight:font/custom_books/server_room_book_arrow_right.png",
        "height": 182, "ascent": 46, "chars": ["\uE024"] },

        { "type": "bitmap", "file": "starlight:font/custom_books/workshop_book_left.png",
        "height": 182, "ascent": 37, "chars": ["\uE031"] },
        { "type": "bitmap", "file": "starlight:font/custom_books/workshop_book_right.png",
        "height": 182, "ascent": 46, "chars": ["\uE032"] },
        { "type": "bitmap", "file": "starlight:font/custom_books/workshop_book_arrow_left.png",
        "height": 182, "ascent": 37, "chars": ["\uE033"] },
        { "type": "bitmap", "file": "starlight:font/custom_books/workshop_book_arrow_right.png",
        "height": 182, "ascent": 46, "chars": ["\uE034"] },

        { "type": "bitmap", "file": "starlight:font/custom_books/hospital_book_left.png",
        "height": 182, "ascent": 37, "chars": ["\uE041"] },
        { "type": "bitmap", "file": "starlight:font/custom_books/hospital_book_right.png",
        "height": 182, "ascent": 46, "chars": ["\uE042"] },
        { "type": "bitmap", "file": "starlight:font/custom_books/hospital_book_arrow_left.png",
        "height": 182, "ascent": 37, "chars": ["\uE043"] },
        { "type": "bitmap", "file": "starlight:font/custom_books/hospital_book_arrow_right.png",
        "height": 182, "ascent": 46, "chars": ["\uE044"] },

        { "type": "bitmap", "file": "starlight:font/custom_books/swimming_pool_book_left.png",
        "height": 182, "ascent": 37, "chars": ["\uE051"] },
        { "type": "bitmap", "file": "starlight:font/custom_books/swimming_pool_book_right.png",
        "height": 182, "ascent": 46, "chars": ["\uE052"] },
        { "type": "bitmap", "file": "starlight:font/custom_books/swimming_pool_book_arrow_left.png",
        "height": 182, "ascent": 37, "chars": ["\uE053"] },
        { "type": "bitmap", "file": "starlight:font/custom_books/swimming_pool_book_arrow_right.png",
        "height": 182, "ascent": 46, "chars": ["\uE054"] },

        { "type": "bitmap", "file": "starlight:font/custom_books/gym_book_left.png",
        "height": 182, "ascent": 37, "chars": ["\uE061"] },
        { "type": "bitmap", "file": "starlight:font/custom_books/gym_book_right.png",
        "height": 182, "ascent": 46, "chars": ["\uE062"] },
        { "type": "bitmap", "file": "starlight:font/custom_books/gym_book_arrow_left.png",
        "height": 182, "ascent": 37, "chars": ["\uE063"] },
        { "type": "bitmap", "file": "starlight:font/custom_books/gym_book_arrow_right.png",
        "height": 182, "ascent": 46, "chars": ["\uE064"] },

        { "type": "bitmap", "file": "starlight:font/custom_books/art_gallery_book_left.png",
        "height": 182, "ascent": 37, "chars": ["\uE071"] },
        { "type": "bitmap", "file": "starlight:font/custom_books/art_gallery_book_right.png",
        "height": 182, "ascent": 46, "chars": ["\uE072"] },
        { "type": "bitmap", "file": "starlight:font/custom_books/art_gallery_book_arrow_left.png",
        "height": 182, "ascent": 37, "chars": ["\uE073"] },
        { "type": "bitmap", "file": "starlight:font/custom_books/art_gallery_book_arrow_right.png",
        "height": 182, "ascent": 46, "chars": ["\uE074"] },

        { "type": "bitmap", "file": "starlight:font/custom_books/pub_book_left.png",
        "height": 182, "ascent": 37, "chars": ["\uE081"] },
        { "type": "bitmap", "file": "starlight:font/custom_books/pub_book_right.png",
        "height": 182, "ascent": 46, "chars": ["\uE082"] },
        { "type": "bitmap", "file": "starlight:font/custom_books/pub_book_arrow_left.png",
        "height": 182, "ascent": 37, "chars": ["\uE083"] },
        { "type": "bitmap", "file": "starlight:font/custom_books/pub_book_arrow_right.png",
        "height": 182, "ascent": 46, "chars": ["\uE084"] },

        { "type": "bitmap", "file": "starlight:font/custom_books/cinema_book_left.png",
        "height": 182, "ascent": 37, "chars": ["\uE091"] },
        { "type": "bitmap", "file": "starlight:font/custom_books/cinema_book_right.png",
        "height": 182, "ascent": 46, "chars": ["\uE092"] },
        { "type": "bitmap", "file": "starlight:font/custom_books/cinema_book_arrow_left.png",
        "height": 182, "ascent": 37, "chars": ["\uE093"] },
        { "type": "bitmap", "file": "starlight:font/custom_books/cinema_book_arrow_right.png",
        "height": 182, "ascent": 46, "chars": ["\uE094"] },

        { "type": "bitmap", "file": "starlight:font/custom_books/kitchen_book_left.png",
        "height": 182, "ascent": 37, "chars": ["\uE0a1"] },
        { "type": "bitmap", "file": "starlight:font/custom_books/kitchen_book_right.png",
        "height": 182, "ascent": 46, "chars": ["\uE0a2"] },
        { "type": "bitmap", "file": "starlight:font/custom_books/kitchen_book_arrow_left.png",
        "height": 182, "ascent": 37, "chars": ["\uE0a3"] },
        { "type": "bitmap", "file": "starlight:font/custom_books/kitchen_book_arrow_right.png",
        "height": 182, "ascent": 46, "chars": ["\uE0a4"] },

        { "type": "bitmap", "file": "starlight:font/custom_books/lab_book_left.png",
        "height": 182, "ascent": 37, "chars": ["\uE0b1"] },
        { "type": "bitmap", "file": "starlight:font/custom_books/lab_book_right.png",
        "height": 182, "ascent": 46, "chars": ["\uE0b2"] },
        { "type": "bitmap", "file": "starlight:font/custom_books/lab_book_arrow_left.png",
        "height": 182, "ascent": 37, "chars": ["\uE0b3"] },
        { "type": "bitmap", "file": "starlight:font/custom_books/lab_book_arrow_right.png",
        "height": 182, "ascent": 46, "chars": ["\uE0b4"] },


        { "type": "bitmap", "file": "starlight:font/custom_books/reference_book/emptyarrow_page_left.png",
        "height": 182, "ascent": 37, "chars": ["\uEEff"] },
        { "type": "bitmap", "file": "starlight:font/custom_books/reference_book/emptyarrow_page_right.png",
        "height": 182, "ascent": 46, "chars": ["\uEF00"] },
        { "type": "bitmap", "file": "starlight:font/custom_books/reference_book/empty_page_left.png",
        "height": 182, "ascent": 37, "chars": ["\uEF01"] },
        { "type": "bitmap", "file": "starlight:font/custom_books/reference_book/empty_page_right.png",
        "height": 182, "ascent": 46, "chars": ["\uEF02"] },
        { "type": "bitmap", "file": "starlight:font/custom_books/reference_book/tool_lvl0_page_left.png",
        "height": 182, "ascent": 37, "chars": ["\uEF03"] },
        { "type": "bitmap", "file": "starlight:font/custom_books/reference_book/tool_lvl0_page_right.png",
        "height": 182, "ascent": 46, "chars": ["\uEF04"] },
        { "type": "bitmap", "file": "starlight:font/custom_books/reference_book/tool_lvl0_page_left.png",
        "height": 182, "ascent": 37, "chars": ["\uEF05"] },
        { "type": "bitmap", "file": "starlight:font/custom_books/reference_book/tool_lvl0_page_right.png",
        "height": 182, "ascent": 46, "chars": ["\uEF06"] },
        { "type": "bitmap", "file": "starlight:font/custom_books/reference_book/tool_lvl0_page_left.png",
        "height": 182, "ascent": 37, "chars": ["\uEF07"] },
        { "type": "bitmap", "file": "starlight:font/custom_books/reference_book/tool_lvl0_page_right.png",
        "height": 182, "ascent": 46, "chars": ["\uEF08"] },
        { "type": "bitmap", "file": "starlight:font/custom_books/reference_book/tool_lvl0_page_left.png",
        "height": 182, "ascent": 37, "chars": ["\uEF09"] },
        { "type": "bitmap", "file": "starlight:font/custom_books/reference_book/tool_lvl0_page_right.png",
        "height": 182, "ascent": 46, "chars": ["\uEF0a"] },
        { "type": "bitmap", "file": "starlight:font/custom_books/reference_book/tool_lvl0_page_left.png",
        "height": 182, "ascent": 37, "chars": ["\uEF0b"] },
        { "type": "bitmap", "file": "starlight:font/custom_books/reference_book/tool_lvl0_page_right.png",
        "height": 182, "ascent": 46, "chars": ["\uEF0c"] },
        { "type": "bitmap", "file": "starlight:font/custom_books/reference_book/cube_page_left.png",
        "height": 182, "ascent": 37, "chars": ["\uEF0d"] },
        { "type": "bitmap", "file": "starlight:font/custom_books/reference_book/cube_page_right.png",
        "height": 182, "ascent": 46, "chars": ["\uEF0e"] },
        { "type": "bitmap", "file": "starlight:font/custom_books/reference_book/emitter_page_left.png",
        "height": 182, "ascent": 37, "chars": ["\uEF0f"] },
        { "type": "bitmap", "file": "starlight:font/custom_books/reference_book/emitter_page_right.png",
        "height": 182, "ascent": 46, "chars": ["\uEF10"] },
        { "type": "bitmap", "file": "starlight:font/custom_books/reference_book/reciever_page_left.png",
        "height": 182, "ascent": 37, "chars": ["\uEF11"] },
        { "type": "bitmap", "file": "starlight:font/custom_books/reference_book/emptyarrow_page_right.png",
        "height": 182, "ascent": 46, "chars": ["\uEF12"] },
        { "type": "bitmap", "file": "starlight:font/custom_books/reference_book/reciever_page_left.png",
        "height": 182, "ascent": 37, "chars": ["\uEF13"] },
        { "type": "bitmap", "file": "starlight:font/custom_books/reference_book/reciever_page_right.png",
        "height": 182, "ascent": 46, "chars": ["\uEF14"] },
        { "type": "bitmap", "file": "starlight:font/custom_books/reference_book/mirror_page_left.png",
        "height": 182, "ascent": 37, "chars": ["\uEF15"] },
        { "type": "bitmap", "file": "starlight:font/custom_books/reference_book/mirror_page_right.png",
        "height": 182, "ascent": 46, "chars": ["\uEF16"] },
        { "type": "bitmap", "file": "starlight:font/custom_books/reference_book/splitter_page_left.png",
        "height": 182, "ascent": 37, "chars": ["\uEF17"] },
        { "type": "bitmap", "file": "starlight:font/custom_books/reference_book/splitter_page_right.png",
        "height": 182, "ascent": 46, "chars": ["\uEF18"] },
        { "type": "bitmap", "file": "starlight:font/custom_books/reference_book/merger_page_left.png",
        "height": 182, "ascent": 37, "chars": ["\uEF19"] },
        { "type": "bitmap", "file": "starlight:font/custom_books/reference_book/merger_page_right.png",
        "height": 182, "ascent": 46, "chars": ["\uEF1a"] },
        { "type": "bitmap", "file": "starlight:font/custom_books/reference_book/rgbsplitter_page_left.png",
        "height": 182, "ascent": 37, "chars": ["\uEF1b"] },
        { "type": "bitmap", "file": "starlight:font/custom_books/reference_book/rgbsplitter_page_right.png",
        "height": 182, "ascent": 46, "chars": ["\uEF1c"] },
        { "type": "bitmap", "file": "starlight:font/custom_books/reference_book/filterwall_page_left.png",
        "height": 182, "ascent": 37, "chars": ["\uEF1d"] },
        { "type": "bitmap", "file": "starlight:font/custom_books/reference_book/filterwall_page_right.png",
        "height": 182, "ascent": 46, "chars": ["\uEF1e"] },
        { "type": "bitmap", "file": "starlight:font/custom_books/reference_book/inverter_page_left.png",
        "height": 182, "ascent": 37, "chars": ["\uEF1f"] },
        { "type": "bitmap", "file": "starlight:font/custom_books/reference_book/inverter_page_right.png",
        "height": 182, "ascent": 46, "chars": ["\uEF20"] },
        { "type": "bitmap", "file": "starlight:font/custom_books/reference_book/colormixer_page_left.png",
        "height": 182, "ascent": 37, "chars": ["\uEF21"] },
        { "type": "bitmap", "file": "starlight:font/custom_books/reference_book/colormixer_page_right.png",
        "height": 182, "ascent": 46, "chars": ["\uEF22"] },
        { "type": "bitmap", "file": "starlight:font/custom_books/reference_book/filterblock_page_left.png",
        "height": 182, "ascent": 37, "chars": ["\uEF23"] },
        { "type": "bitmap", "file": "starlight:font/custom_books/reference_book/filterblock_page_right.png",
        "height": 182, "ascent": 46, "chars": ["\uEF24"] },
        { "type": "bitmap", "file": "starlight:font/custom_books/reference_book/spinner_page_left.png",
        "height": 182, "ascent": 37, "chars": ["\uEF25"] },
        { "type": "bitmap", "file": "starlight:font/custom_books/reference_book/spinner_page_right.png",
        "height": 182, "ascent": 46, "chars": ["\uEF26"] },
        { "type": "bitmap", "file": "starlight:font/custom_books/reference_book/laserporter_page_left.png",
        "height": 182, "ascent": 37, "chars": ["\uEF27"] },
        { "type": "bitmap", "file": "starlight:font/custom_books/reference_book/laserporter_page_right.png",
        "height": 182, "ascent": 46, "chars": ["\uEF28"] },
        { "type": "bitmap", "file": "starlight:font/custom_books/reference_book/redstone_page_left.png",
        "height": 182, "ascent": 37, "chars": ["\uEF29"] },
        { "type": "bitmap", "file": "starlight:font/custom_books/reference_book/redstone_page_right.png",
        "height": 182, "ascent": 46, "chars": ["\uEF2a"] },
        { "type": "bitmap", "file": "starlight:font/custom_books/reference_book/redstonetorch_page_left.png",
        "height": 182, "ascent": 37, "chars": ["\uEF2b"] },
        { "type": "bitmap", "file": "starlight:font/custom_books/reference_book/redstonetorch_page_right.png",
        "height": 182, "ascent": 46, "chars": ["\uEF2c"] },
        { "type": "bitmap", "file": "starlight:font/custom_books/reference_book/converter_page_left.png",
        "height": 182, "ascent": 37, "chars": ["\uEF2d"] },
        { "type": "bitmap", "file": "starlight:font/custom_books/reference_book/converter_page_right.png",
        "height": 182, "ascent": 46, "chars": ["\uEF2e"] },
        { "type": "bitmap", "file": "starlight:font/custom_books/reference_book/fizzler_page_left.png",
        "height": 182, "ascent": 37, "chars": ["\uEF2f"] },
        { "type": "bitmap", "file": "starlight:font/custom_books/reference_book/fizzler_page_right.png",
        "height": 182, "ascent": 46, "chars": ["\uEF30"] },
		{ "type": "bitmap", "file": "starlight:font/custom_books/reference_book/merger_page_left.png",
        "height": 182, "ascent": 37, "chars": ["\uEF31"] },
        { "type": "bitmap", "file": "starlight:font/custom_books/reference_book/merger_page_right.png",
        "height": 182, "ascent": 46, "chars": ["\uEF32"] },

        { "type": "bitmap", "file": "starlight:font/logo.png",
        "height": 64, "ascent": 26, "chars": ["\uEfa1\uEfa2\uEfa3\uEfa4"] },
        { "type": "bitmap", "file": "starlight:font/logo_matrix.png",
        "height": 64, "ascent": 26, "chars": ["\uEfa5\uEfa6\uEfa7\uEfa8"] },

        { "type": "bitmap", "file": "starlight:font/cycle_around_symbol.png",
        "height": 10, "ascent": 8, "chars": ["\uEff0"] },
        { "type": "bitmap", "file": "starlight:font/green_holo.png",
        "height": 64, "ascent": 15, "chars": ["\uFFFF"] }
    ]
}
